[
  {
    "symbol": "AAPL",
    "name": "Apple Inc",
    "market_cap": 3192676418000.0,
    "real_data": true,
    "rank": 1,
    "weight": 11.94
  },
  {
    "symbol": "MSFT",
    "name": "Microsoft Corporation",
    "market_cap": 3797136179000.0,
    "real_data": true,
    "rank": 2,
    "weight": 10.2
  },
  {
    "symbol": "NVDA",
    "name": "NVIDIA Corporation",
    "market_cap": 4237101892000.0,
    "real_data": true,
    "rank": 3,
    "weight": 7.52
  },
  {
    "symbol": "AMZN",
    "name": "Amazon.com Inc",
    "market_cap": 2465446494000.0,
    "real_data": true,
    "rank": 4,
    "weight": 6.82
  },
  {
    "symbol": "META",
    "name": "Meta Platforms Inc.",
    "market_cap": 1797243142000.0,
    "real_data": true,
    "rank": 5,
    "weight": 4.99
  },
  {
    "symbol": "TSLA",
    "name": "Tesla Inc",
    "market_cap": 983359029000.0,
    "real_data": true,
    "rank": 6,
    "weight": 3.53
  },
  {
    "symbol": "GOOG",
    "name": "Alphabet Inc Class C",
    "market_cap": 2329702302000.0,
    "real_data": true,
    "rank": 7,
    "weight": 3.49
  },
  {
    "symbol": "GOOGL",
    "name": "Alphabet Inc Class A",
    "market_cap": 2338997142000.0,
    "real_data": true,
    "rank": 8,
    "weight": 3.15
  },
  {
    "symbol": "AVGO",
    "name": "Broadcom Inc",
    "market_cap": 1357938819000.0,
    "real_data": true,
    "rank": 9,
    "weight": 2.79
  },
  {
    "symbol": "COST",
    "name": "Costco Wholesale Corp",
    "market_cap": 414118806000.0,
    "real_data": true,
    "rank": 10,
    "weight": 2.21
  },
  {
    "symbol": "CSCO",
    "name": "Cisco Systems Inc.",
    "weight": 1.95,
    "rank": 11
  },
  {
    "symbol": "ADBE",
    "name": "Adobe Inc.",
    "weight": 1.92,
    "rank": 12
  },
  {
    "symbol": "TMUS",
    "name": "T-Mobile US Inc.",
    "weight": 1.87,
    "rank": 13
  },
  {
    "symbol": "AMD",
    "name": "Advanced Micro Devices Inc.",
    "weight": 1.49,
    "rank": 14
  },
  {
    "symbol": "PEP",
    "name": "PepsiCo Inc.",
    "weight": 1.47,
    "rank": 15
  },
  {
    "symbol": "NFLX",
    "name": "Netflix Inc.",
    "weight": 1.38,
    "rank": 16
  },
  {
    "symbol": "CMCSA",
    "name": "Comcast Corp. Class A",
    "weight": 1.37,
    "rank": 17
  },
  {
    "symbol": "INTU",
    "name": "Intuit Inc.",
    "weight": 1.33,
    "rank": 18
  },
  {
    "symbol": "QCOM",
    "name": "Qualcomm Inc.",
    "weight": 1.19,
    "rank": 19
  },
  {
    "symbol": "TXN",
    "name": "Texas Instruments Inc.",
    "weight": 1.15,
    "rank": 20
  }
]